youtube/Channel.py
youtube/HtmlEntityDefs.py
youtube/Playlist.py
youtube/Search.py
youtube/Video.py
youtube/__init__.py
simpleyoutubedata-0.0.55.dist-info/LICENSE
simpleyoutubedata-0.0.55.dist-info/METADATA
simpleyoutubedata-0.0.55.dist-info/WHEEL
simpleyoutubedata-0.0.55.dist-info/top_level.txt
simpleyoutubedata-0.0.55.dist-info/RECORD
