Metadata-Version: 2.1
Name: simpleyoutubedata
Version: 0.0.55
Summary: Python youtube-api-for-python wrapper
Home-page: UNKNOWN
Author: Katistic
License: MIT
Platform: UNKNOWN
Classifier: Intended Audience :: Developers
Classifier: Natural Language :: English
Classifier: Operating System :: OS Independent
Classifier: Programming Language :: Python :: 3.5
Classifier: Programming Language :: Python :: 3.6
Classifier: Programming Language :: Python :: 3.7
Classifier: Topic :: Internet
Classifier: Topic :: Utilities
Requires-Python: >=3.5.3
Requires-Dist: google-api-python-client
Requires-Dist: google-auth-oauthlib
Requires-Dist: google-auth-httplib2
